{
	"status": true,
	"message": null,
	"data": [
		{
			"ASSEMBLY_CODE_NAME": "Battery",
			"ACTION_CODE_NAME": 29,
			"DEFECT_CODE_NAME": "HEAT04",
			"PART_DESC": "ASSY-BATT 4C 48WH 4.21AH LI RR03048XL-PR",
			"ACTION_NOTE": "CAB140",
			"FA_FF_VALUE": "CID",
			"DEFECT_NOTE": "851610-855S",
			"ASSEMBLY_CODE_DESC": "Battery",
			"ACTION_CODE_DESC": "Replacement - primary cause",
			"DEFECT_CODE_DESC": "Unit overheating issues",
			"COMPLETE_PART": "ASSY-BATT 4C 48WH 4.21AH LI RR03048XL-PR - 851610-855S"
		}, {
			"ASSEMBLY_CODE_NAME": "Battery",
			"ACTION_CODE_NAME": 29,
			"DEFECT_CODE_NAME": "HEAT04",
			"PART_DESC": "ASSY-BATT 4C 48WH 4.21AH LI RR03048XL-PR",
			"ACTION_NOTE": "CAB142",
			"FA_FF_VALUE": "CID",
			"DEFECT_NOTE": "851610-855S",
			"ASSEMBLY_CODE_DESC": "Battery",
			"ACTION_CODE_DESC": "Replacement - primary cause",
			"DEFECT_CODE_DESC": "Unit overheating issues",
			"COMPLETE_PART": "ASSY-BATT 4C 48WH 4.21AH LI RR03048XL-PR - 851610-855S"
		},
        {
            "ASSEMBLY_CODE_NAME": "PC BOARD",
            "ACTION_CODE_NAME": 29,
            "DEFECT_CODE_NAME": "DPKE01",
            "PART_DESC": "PCBA, HDD BOARD",
            "ACTION_NOTE": null,
            "FA_FF_VALUE": "IW",
            "DEFECT_NOTE": "L24589-001",
            "ASSEMBLY_CODE_DESC": "PCB - Audio, USB, etc.",
            "ACTION_CODE_DESC": "Replacement - primary cause",
            "DEFECT_CODE_DESC": "Windows DPK key issue",
            "COMPLETE_PART": "PCBA, HDD BOARD - L24589-001"
        },{
		"ASSEMBLY_CODE_NAME": "FAN-HEATS",
		"ACTION_CODE_NAME": 29,
		"DEFECT_CODE_NAME": "HEAT03",
		"PART_DESC": null,
		"ACTION_NOTE": null,
		"FA_FF_VALUE": "IW",
		"DEFECT_NOTE": "L24589-001",
		"ASSEMBLY_CODE_DESC": "Fan - Heatsink",
		"ACTION_CODE_DESC": "Replacement - primary cause",
		"DEFECT_CODE_DESC": "FAN NOISE",
		"COMPLETE_PART": " - "
	},
	{
		"ASSEMBLY_CODE_NAME": "PC BOARD",
		"ACTION_CODE_NAME": 29,
		"DEFECT_CODE_NAME": "DPKE01",
		"PART_DESC": "PCBA, HDD BOARD",
		"ACTION_NOTE": null,
		"FA_FF_VALUE": "CID",
		"DEFECT_NOTE": "L24589-001",
		"ASSEMBLY_CODE_DESC": "PCB - Audio, USB, etc.",
		"ACTION_CODE_DESC": "Replacement - primary cause",
		"DEFECT_CODE_DESC": "Windows DPK key issue",
		"COMPLETE_PART": "PCBA, HDD BOARD - L24589-001"
	}
]
}