{
  "data": [
    {      
      "partNumber": "JU093 - ADPT,AC,65W,CHNY,3P",
      "defect": "No Power",
      "commodity": "HDD",
      "primaryFault": false
    },
    {
      "bgt": "L23",
      "bcv": "L23",
      "partNumber": "TK238 - ADPT,AC,65W,CHNY,3P",
      "defect": "No Power",
      "commodity": "CABLES AND CORDS",
      "primaryFault": false
    },
    {
      "part": "0XJH4 - ADPT,AC,65W,CHNY,3P",
      "defectCode": "ECN",
      "commodity": "BATTERY",
      "primaryFault": false
    },
    {
      "part": "U733K - ADPT,AC,65W,CHNY,3P",
      "defect": "BLUETOOTH Hardware",
      "commodity": "BLUETOOTH CHIP",
      "doa": "DOA",
      "goodPartShelf": "Part Unused"
    },
    {
      "part": "YFKXK - ADPT,AC,65W,CHNY,3P",
      "defect": "BLUETOOTH Hardware",
      "commodity": "CABLES AND CORDS",
      "doa": "DOA",
      "goodPartShelf": "Part Unused",
      "primaryFault": false
    }
  ],
  "status": true,
  "message": null
}