{
    "data" : [
        {
        "icon":"hourglass_empty",
        "date":"01/02/2021",
        "wikiTitle":"Notebook PCs, HP ZBook Firefly 14, 15 G7 Mobile Workstations",
        "author":"chhail",
        "exp":"all",
        "family":"mast",
        "platform":"all",
        "modelName":"all",
        "workCenter":"receiving",
        "language":"ENGLISH-EN"
         },
        {
        "icon":"hourglass_empty",
        "date":"13/04/2022",
        "wikiTitle":"Workstations - Systems BIOS Updates Will Use Windows Updates",
        "author":"john",
        "exp":"ex",
        "family":"fam",
        "platform":"plat",
        "modelName":"all",
        "workCenter":"debug",
        "language":"ENGLISH-EN"
        }
    ],
    "message": null,
    "status": true
}