{
  "ctype": "page",
  "uuid": "pageUUID",
  "css": "",
  "visibility": true,
  "hooks": [],
  "validations": [],
  "action": [],
  "header": [
    {
      "ctype": "toolbar",
      "toolbarClass": "searchCriteria-toolbar section-title",
      "items": [
        {
          "ctype": "title",
          "title": "Repair - Debug"
        }
      ]
    }
  ],
  "items": [
    {
      "ctype": "title",
      "uuid": "searchCriteriaErrorTitleUUID",
      "titleClass": "error-title",
      "isShown": false
    },
    {
      "ctype": "formPanel",
      "title": "Discrepancy",
      "header": "",
      "uuid": "discrepancyUUID",
      "formPanelClass": "searchCriteria-panel",
      "visibility": true,
      "hooks": [],
      "validations": [],
      "actions": [],
      "items": [
        {
          "ctype": "nativeDropdown",
          "uuid": "discrepancyTypeUUID",
          "hooks": [],
          "validations": [],
          "actions": [
            {
              "type": "context",
              "config": {
                "requestMethod": "add",
                "key": "userOptionSerialNumber",
                "data": "elementControlValue"
              },
              "eventSource": "change"
            }
          ],
          "type": "text",
          "required": true,
          "submitable": true,
          "label": "",
          "labelPosition": "",
          "name": "identificatorTypeForDiscrepancy",
          "defaultValue": "#userOptionSerialNumber",
          "dropdownClass": "searchcriteris-drpdwn",
          "options": [
            {
              "code": "BCN",
              "displayValue": "Barcode Number",
              "isDefault":true
            },
            {
              "code": "InboundTN",
              "displayValue": "Inbound TN"
            },
            {
              "code": "OutboundTN",
              "displayValue": "Outbound TN"
            },
            {
              "code": "FixedAssetTag",
              "displayValue": "Fixed Asset Tag"
            },
            {
              "code": "SerialNumber",
              "displayValue": "Serial Number"
            }
          ]
        },
        {
          "ctype": "textField",
          "uuid": "discrepancyUnitValueUUID",
          "hooks": [],
          "validations": [],
          "textfieldClass": "searchcriteris-text",
          "type": "text",
          "required": true,
          "placeholder": "Scan Serial Number",
          "submitable": true,
          "label": "",
          "labelPosition": "",
          "name": "discrepancyunitIdentificationValue",
          "prefix": "true",
          "prefixIcon": "qr_code_scanner",
          "suffix": true,
          "suffixIcon": "arrow_forward",
          "actions": [
            {
              "type": "context",
              "config": {
                "key": "discrepancyUserSearchCriteria",
                "data": "formData",
                "requestMethod": "add"
              },
              "eventSource": "click"
            },
            {
              "type": "microservice",
              "config": {
                "microserviceId": "getUnitInfo",
                "requestMethod": "get",
                "params": {
                  "unitIdentificationValue": "#discrepancyUserSearchCriteria.discrepancyunitIdentificationValue",
                  "identificatorType": "#discrepancyUserSearchCriteria.identificatorTypeForDiscrepancy"
                }
              },
              "eventSource": "click",
              "responseDependents": {
                "onSuccess": {
                  "actions": [
                    {
                      "type": "context",
                      "config": {
                        "requestMethod": "add",
                        "key": "repairUnitInfo",
                        "data": "responseData"
                      }
                    },
                    {
                      "type": "condition",
                      "config": {
                        "operation": "isEqualTo",
                        "lhs": "#repairUnitInfo.ONHOLD",
                        "rhs": "1"
                      },
                      "responseDependents": {
                        "onSuccess": {
                          "actions": [
                            {
                              "type": "updateComponent",
                              "config": {
                                "key": "searchCriteriaErrorTitleUUID",
                                "properties": {
                                  "titleValue": "HOLDERROR: Unit can't be processed, as this is currently on hold, Storage IS NOT same as the one on the workorder",
                                  "isShown": true
                                }
                              }
                            }
                          ]
                        },
                        "onFailure": {
                          "actions": [
                            {
                              "type": "condition",
                              "config": {
                                "operation": "isEqualTo",
                                "lhs": "#repairUnitInfo.STATUS",
                                "rhs": "Time Out"
                              },
                              "responseDependents": {
                                "onSuccess": {
                                  "actions": [
                                    {
                                      "type": "condition",
                                      "config": {
                                        "operation": "isValid",
                                        "lhs": "#repairUnitInfo.DESTINATIONWC"
                                      },
                                      "responseDependents": {
                                        "onSuccess": {
                                          "actions": [
                                            {
                                              "type": "microservice",
                                              "config": {
                                                "microserviceId": "performTimeIn",
                                                "requestMethod": "post",
                                                "body": {
                                                  "timeInRequest": {
                                                    "workCenter": "#repairUnitInfo.DESTINATIONWC",
                                                    "location": "#repairUnitInfo.GEONAME",
                                                    "part": "#repairUnitInfo.PART_NO",
                                                    "bcn": "#repairUnitInfo.ITEM_BCN",
                                                    "serialNumber": "#repairUnitInfo.SERIAL_NO",
                                                    "password": "#loginUUID.password"
                                                  },
                                                  "SesCustomer": 1,
                                                  "userName": "#loginUUID.username",
                                                  "userPass": "#loginUUID.password",
                                                  "ip": "::1",
                                                  "callSource": "FrontEnd",
                                                  "apiUsage_LocationName": "#repairUnitInfo.GEONAME",
                                                  "apiUsage_ClientName": "#repairUnitInfo.CLIENTNAME"
                                                },
                                                "toBeStringified": true
                                              },
                                              "responseDependents": {
                                                "onSuccess": {
                                                  "actions": [
                                                    {
                                                      "type": "microservice",
                                                      "config": {
                                                        "microserviceId": "getUnitInfo",
                                                        "requestMethod": "get",
                                                        "params": {
                                                          "unitIdentificationValue": "#discrepancyUserSearchCriteria.discrepancyunitIdentificationValue",
                                                          "identificatorType": "#discrepancyUserSearchCriteria.identificatorTypeForDiscrepancy"
                                                        }
                                                      },
                                                      "eventSource": "click",
                                                      "responseDependents": {
                                                        "onSuccess": {
                                                          "actions": [
                                                            {
                                                              "type": "context",
                                                              "config": {
                                                                "requestMethod": "add",
                                                                "key": "repairUnitInfo",
                                                                "data": "responseData"
                                                              }
                                                            },
                                                            {
                                                              "type": "microservice",
                                                              "config": {
                                                                "microserviceId": "receiptDate",
                                                                "requestMethod": "get",
                                                                "params": {
                                                                  "locationId": "#repairUnitInfo.LOCATION_ID",
                                                                  "itemId": "#repairUnitInfo.ITEM_ID",
                                                                  "userName": "#userAccountInfo.PersonalDetails.USERID",
                                                                  "bcn": "#repairUnitInfo.ITEM_BCN",
                                                                  "orderId": "#ROByBCNForDiscrepancy"
                                                                }
                                                              },
                                                              "responseDependents": {
                                                                "onSuccess": {
                                                                  "actions": [
                                                                    {
                                                                      "type": "context",
                                                                      "config": {
                                                                        "requestMethod": "add",
                                                                        "key": "receiptDateForDiscrepancy",
                                                                        "data": "responseData"
                                                                      }
                                                                    },
                                                                    {
                                                                      "type": "dateFormat",
                                                                      "config": {
                                                                        "format": "dd MMM, yyy",
                                                                        "dateKey": "localDateTime",
                                                                        "targetKey": "tat",
                                                                        "source": "#receiptDateForDiscrepancy"
                                                                      }
                                                                    },
                                                                    {
                                                                      "type": "microservice",
                                                                      "config": {
                                                                        "microserviceId": "getPartModelAndWarrentyDetails",
                                                                        "requestMethod": "get",
                                                                        "params": {
                                                                          "locationId": "#repairUnitInfo.LOCATION_ID",
                                                                          "clinetId": "#repairUnitInfo.CLIENT_ID",
                                                                          "contractId": "#repairUnitInfo.CONTRACT_ID",
                                                                          "reforderId": "#ROByBCNForDiscrepancy",
                                                                          "partNumber": "#repairUnitInfo.PART_NO",
                                                                          "userName": "#userAccountInfo.PersonalDetails.USERID"
                                                                        }
                                                                      },
                                                                      "responseDependents": {
                                                                        "onSuccess": {
                                                                          "actions": [
                                                                            {
                                                                              "type": "context",
                                                                              "config": {
                                                                                "requestMethod": "add",
                                                                                "key": "discrepancyPartAndWarrantyDetails",
                                                                                "data": "responseData"
                                                                              }
                                                                            },
                                                                            {
                                                                              "type": "microservice",
                                                                              "config": {
                                                                                "microserviceId": "getResultCodeForDiscrepancy",
                                                                                "requestMethod": "get",
                                                                                "params": {
                                                                                  "bcn": "#repairUnitInfo.ITEM_BCN",
                                                                                  "validateResult": 1
                                                                                }
                                                                              },
                                                                              "responseDependents": {
                                                                                "onSuccess": {
                                                                                  "actions": [
                                                                                    {
                                                                                      "type": "context",
                                                                                      "config": {
                                                                                        "requestMethod": "add",
                                                                                        "key": "resultCodesForDiscrepancy",
                                                                                        "data": "responseData"
                                                                                      }
                                                                                    },
                                                                                    {
                                                                                      "type": "microservice",
                                                                                      "config": {
                                                                                        "microserviceId": "getstorageholdsubcode",
                                                                                        "requestMethod": "get",
                                                                                        "params": {
                                                                                          "locationId": "#repairUnitInfo.LOCATION_ID",
                                                                                          "clientId": "#repairUnitInfo.CLIENT_ID",
                                                                                          "contractId": "#repairUnitInfo.CONTRACT_ID",
                                                                                          "route": "#repairUnitInfo.ROUTE",
                                                                                          "username": "#userAccountInfo.PersonalDetails.USERID",
                                                                                          "workCenterId": "#repairUnitInfo.WORKCENTER_ID"
                                                                                        }
                                                                                      },
                                                                                      "responseDependents": {
                                                                                        "onSuccess": {
                                                                                          "actions": [
                                                                                            {
                                                                                              "type": "context",
                                                                                              "config": {
                                                                                                "requestMethod": "add",
                                                                                                "key": "holdCodesForDiscrepancy",
                                                                                                "data": "responseData"
                                                                                              }
                                                                                            },
                                                                                            {
                                                                                              "type": "condition",
                                                                                              "config": {
                                                                                                "operation": "isValid",
                                                                                                "lhs": "#repairUnitInfo.ROUTE_ID"
                                                                                              },
                                                                                              "responseDependents": {
                                                                                                "onSuccess": {
                                                                                                  "actions": [
                                                                                                    {
                                                                                                      "type": "condition",
                                                                                                      "config": {
                                                                                                        "operation": "isValid",
                                                                                                        "lhs": "#repairUnitInfo.WORKCENTER_ID"
                                                                                                      },
                                                                                                      "responseDependents": {
                                                                                                        "onSuccess": {
                                                                                                          "actions": [
                                                                                                            {
                                                                                                              "type": "microservice",
                                                                                                              "config": {
                                                                                                                "microserviceId": "getSubProcessMenu",
                                                                                                                "requestMethod": "get",
                                                                                                                "params": {
                                                                                                                  "userId": "#loginUUID.username",
                                                                                                                  "locationId": "#userSelectedLocation",
                                                                                                                  "clientId": "#userSelectedClient",
                                                                                                                  "contractId": "#userSelectedContract",
                                                                                                                  "wcId": "#repairUnitInfo.WORKCENTER_ID",
                                                                                                                  "optId": "#repairUnitInfo.ROUTE_ID",
                                                                                                                  "btt": "",
                                                                                                                  "whId": "#repairUnitInfo.WAREHOUSE_ID",
                                                                                                                  "operationType": "#userSelectedSubProcessType",
                                                                                                                  "workCenterName": "#repairUnitInfo.WORKCENTER"
                                                                                                                }
                                                                                                              },
                                                                                                              "responseDependents": {
                                                                                                                "onSuccess": {
                                                                                                                  "actions": [
                                                                                                                    {
                                                                                                                      "type": "context",
                                                                                                                      "config": {
                                                                                                                        "requestMethod": "add",
                                                                                                                        "key": "SubprocessMenu",
                                                                                                                        "data": "responseData"
                                                                                                                      }
                                                                                                                    },
                                                                                                                    {
                                                                                                                      "type": "microservice",
                                                                                                                      "config": {
                                                                                                                        "microserviceId": "getTimeInDetails",
                                                                                                                        "requestMethod": "get",
                                                                                                                        "params": {
                                                                                                                          "workCenterName": "#repairUnitInfo.WORKCENTER",
                                                                                                                          "itemId": "#repairUnitInfo.ITEM_ID",
                                                                                                                          "userName": "#userAccountInfo.PersonalDetails.USERID",
                                                                                                                          "locationId": "#repairUnitInfo.LOCATION_ID"
                                                                                                                        }
                                                                                                                      },
                                                                                                                      "responseDependents": {
                                                                                                                        "onSuccess": {
                                                                                                                          "actions": [
                                                                                                                            {
                                                                                                                              "type": "updateComponent",
                                                                                                                              "config": {
                                                                                                                                "key": "errorTitleUUID",
                                                                                                                                "properties": {
                                                                                                                                  "titleValue": "",
                                                                                                                                  "isShown": false
                                                                                                                                }
                                                                                                                              }
                                                                                                                            },
                                                                                                                            {
                                                                                                                              "type": "context",
                                                                                                                              "config": {
                                                                                                                                "requestMethod": "add",
                                                                                                                                "key": "getTimeInDetailsResp",
                                                                                                                                "data": "responseData"
                                                                                                                              }
                                                                                                                            },
                                                                                                                            {
                                                                                                                              "type": "renderTemplate",
                                                                                                                              "config": {
                                                                                                                                "templateId": "repairAssessmentScreen.json",
                                                                                                                                "mode": "local"
                                                                                                                              }
                                                                                                                            }
                                                                                                                          ]
                                                                                                                        },
                                                                                                                        "onFailure": {
                                                                                                                          "actions": [
                                                                                                                            {
                                                                                                                              "type": "context",
                                                                                                                              "config": {
                                                                                                                                "requestMethod": "add",
                                                                                                                                "key": "getTimeInDetailsResp",
                                                                                                                                "data": "responseData"
                                                                                                                              }
                                                                                                                            },
                                                                                                                            {
                                                                                                                              "type": "updateComponent",
                                                                                                                              "config": {
                                                                                                                                "key": "searchCriteriaErrorTitleUUID",
                                                                                                                                "properties": {
                                                                                                                                  "titleValue": "#getTimeInDetailsResp",
                                                                                                                                  "isShown": true
                                                                                                                                }
                                                                                                                              }
                                                                                                                            }
                                                                                                                          ]
                                                                                                                        }
                                                                                                                      }
                                                                                                                    }
                                                                                                                  ]
                                                                                                                },
                                                                                                                "onFailure": {
                                                                                                                  "actions": [
                                                                                                                    {
                                                                                                                      "type": "context",
                                                                                                                      "config": {
                                                                                                                        "requestMethod": "add",
                                                                                                                        "key": "permission",
                                                                                                                        "data": "responseData"
                                                                                                                      }
                                                                                                                    },
                                                                                                                    {
                                                                                                                      "type": "updateComponent",
                                                                                                                      "config": {
                                                                                                                        "key": "searchCriteriaErrorTitleUUID",
                                                                                                                        "properties": {
                                                                                                                          "titleValue": "#permission",
                                                                                                                          "isShown": true
                                                                                                                        }
                                                                                                                      }
                                                                                                                    }
                                                                                                                  ]
                                                                                                                }
                                                                                                              }
                                                                                                            }
                                                                                                          ]
                                                                                                        },
                                                                                                        "onFailure": {
                                                                                                          "actions": [
                                                                                                            {
                                                                                                              "type": "updateComponent",
                                                                                                              "config": {
                                                                                                                "key": "searchCriteriaErrorTitleUUID",
                                                                                                                "properties": {
                                                                                                                  "titleValue": "WorkCenter Is Not Assigned",
                                                                                                                  "isShown": true
                                                                                                                }
                                                                                                              }
                                                                                                            }
                                                                                                          ]
                                                                                                        }
                                                                                                      }
                                                                                                    }
                                                                                                  ]
                                                                                                },
                                                                                                "onFailure": {
                                                                                                  "actions": [
                                                                                                    {
                                                                                                      "type": "updateComponent",
                                                                                                      "config": {
                                                                                                        "key": "searchCriteriaErrorTitleUUID",
                                                                                                        "properties": {
                                                                                                          "titleValue": "Order Process Type Is Empty",
                                                                                                          "isShown": true
                                                                                                        }
                                                                                                      }
                                                                                                    }
                                                                                                  ]
                                                                                                }
                                                                                              }
                                                                                            }
                                                                                          ]
                                                                                        },
                                                                                        "onFailure": {
                                                                                          "actions": [
                                                                                            {
                                                                                              "type": "context",
                                                                                              "config": {
                                                                                                "requestMethod": "add",
                                                                                                "key": "errorDisp",
                                                                                                "data": "responseData"
                                                                                              }
                                                                                            },
                                                                                            {
                                                                                              "type": "updateComponent",
                                                                                              "config": {
                                                                                                "key": "searchCriteriaErrorTitleUUID",
                                                                                                "properties": {
                                                                                                  "titleValue": "#errorDisp",
                                                                                                  "isShown": true
                                                                                                }
                                                                                              }
                                                                                            }
                                                                                          ]
                                                                                        }
                                                                                      }
                                                                                    }
                                                                                  ]
                                                                                },
                                                                                "onFailure": {
                                                                                  "actions": [
                                                                                    {
                                                                                      "type": "context",
                                                                                      "config": {
                                                                                        "requestMethod": "add",
                                                                                        "key": "errorDisp",
                                                                                        "data": "responseData"
                                                                                      }
                                                                                    },
                                                                                    {
                                                                                      "type": "updateComponent",
                                                                                      "config": {
                                                                                        "key": "searchCriteriaErrorTitleUUID",
                                                                                        "properties": {
                                                                                          "titleValue": "#errorDisp",
                                                                                          "isShown": true
                                                                                        }
                                                                                      }
                                                                                    }
                                                                                  ]
                                                                                }
                                                                              }
                                                                            }
                                                                          ]
                                                                        },
                                                                        "onFailure": {
                                                                          "actions": [
                                                                            {
                                                                              "type": "context",
                                                                              "config": {
                                                                                "requestMethod": "add",
                                                                                "key": "errorDisp",
                                                                                "data": "responseData"
                                                                              }
                                                                            },
                                                                            {
                                                                              "type": "updateComponent",
                                                                              "config": {
                                                                                "key": "searchCriteriaErrorTitleUUID",
                                                                                "properties": {
                                                                                  "titleValue": "#errorDisp",
                                                                                  "isShown": true
                                                                                }
                                                                              }
                                                                            }
                                                                          ]
                                                                        }
                                                                      }
                                                                    }
                                                                  ]
                                                                },
                                                                "onFailure": {
                                                                  "actions": [
                                                                    {
                                                                      "type": "context",
                                                                      "config": {
                                                                        "requestMethod": "add",
                                                                        "key": "errorDisp",
                                                                        "data": "responseData"
                                                                      }
                                                                    },
                                                                    {
                                                                      "type": "updateComponent",
                                                                      "config": {
                                                                        "key": "searchCriteriaErrorTitleUUID",
                                                                        "properties": {
                                                                          "titleValue": "#errorDisp",
                                                                          "isShown": true
                                                                        }
                                                                      }
                                                                    }
                                                                  ]
                                                                }
                                                              }
                                                            }
                                                          ]
                                                        },
                                                        "onFailure": {
                                                          "actions": [
                                                            {
                                                              "type": "context",
                                                              "config": {
                                                                "requestMethod": "add",
                                                                "key": "titleError",
                                                                "data": "responseData"
                                                              }
                                                            },
                                                            {
                                                              "type": "updateComponent",
                                                              "config": {
                                                                "key": "searchCriteriaErrorTitleUUID",
                                                                "properties": {
                                                                  "titleValue": "#titleError",
                                                                  "isShown": true
                                                                }
                                                              }
                                                            }
                                                          ]
                                                        }
                                                      }
                                                    }
                                                  ]
                                                },
                                                "onFailure": {
                                                  "actions": [
                                                    {
                                                      "type": "context",
                                                      "config": {
                                                        "requestMethod": "add",
                                                        "key": "timeinError",
                                                        "data": "responseData"
                                                      }
                                                    },
                                                    {
                                                      "type": "updateComponent",
                                                      "config": {
                                                        "key": "searchCriteriaErrorTitleUUID",
                                                        "properties": {
                                                          "titleValue": "#timeinError",
                                                          "isShown": true
                                                        }
                                                      }
                                                    }
                                                  ]
                                                }
                                              }
                                            }
                                          ]
                                        },
                                        "onFailure": {
                                          "actions": [
                                            {
                                              "type": "errorPrepareAndRender",
                                              "config": {
                                                "key": "searchCriteriaErrorTitleUUID",
                                                "properties": {
                                                  "titleValue": "Item- {0} Reached to it's Destination Workcenter: {1}",
                                                  "isShown": true
                                                },
                                                "valueArray": [
                                                  "#repairUnitInfo.ITEM_BCN",
                                                  "#repairUnitInfo.WORKCENTER"
                                                ]
                                              }
                                            }
                                          ]
                                        }
                                      }
                                    }
                                  ]
                                },
                                "onFailure": {
                                  "actions": [
                                    {
                                      "type": "microservice",
                                      "config": {
                                        "microserviceId": "getROByBCN",
                                        "requestMethod": "get",
                                        "params": {
                                          "userName": "#userAccountInfo.PersonalDetails.USERID",
                                          "itemBCN": "#repairUnitInfo.ITEM_BCN"
                                        }
                                      },
                                      "responseDependents": {
                                        "onSuccess": {
                                          "actions": [
                                            {
                                              "type": "context",
                                              "config": {
                                                "requestMethod": "add",
                                                "key": "ROByBCNForDiscrepancy",
                                                "data": "responseData"
                                              }
                                            },
                                            {
                                              "type": "microservice",
                                              "config": {
                                                "microserviceId": "receiptDate",
                                                "requestMethod": "get",
                                                "params": {
                                                  "locationId": "#repairUnitInfo.LOCATION_ID",
                                                  "itemId": "#repairUnitInfo.ITEM_ID",
                                                  "userName": "#userAccountInfo.PersonalDetails.USERID",
                                                  "bcn": "#repairUnitInfo.ITEM_BCN",
                                                  "orderId": "#ROByBCNForDiscrepancy"
                                                }
                                              },
                                              "responseDependents": {
                                                "onSuccess": {
                                                  "actions": [
                                                    {
                                                      "type": "context",
                                                      "config": {
                                                        "requestMethod": "add",
                                                        "key": "receiptDateForDiscrepancy",
                                                        "data": "responseData"
                                                      }
                                                    },
                                                    {
                                                      "type": "dateFormat",
                                                      "config": {
                                                        "format": "dd MMM, yyy",
                                                        "dateKey": "localDateTime",
                                                        "targetKey": "tat",
                                                        "source": "#receiptDateForDiscrepancy"
                                                      }
                                                    },
                                                    {
                                                      "type": "microservice",
                                                      "config": {
                                                        "microserviceId": "getPartModelAndWarrentyDetails",
                                                        "requestMethod": "get",
                                                        "params": {
                                                          "locationId": "#repairUnitInfo.LOCATION_ID",
                                                          "clinetId": "#repairUnitInfo.CLIENT_ID",
                                                          "contractId": "#repairUnitInfo.CONTRACT_ID",
                                                          "reforderId": "#ROByBCNForDiscrepancy",
                                                          "partNumber": "#repairUnitInfo.PART_NO",
                                                          "userName": "#userAccountInfo.PersonalDetails.USERID"
                                                        }
                                                      },
                                                      "responseDependents": {
                                                        "onSuccess": {
                                                          "actions": [
                                                            {
                                                              "type": "context",
                                                              "config": {
                                                                "requestMethod": "add",
                                                                "key": "discrepancyPartAndWarrantyDetails",
                                                                "data": "responseData"
                                                              }
                                                            },
                                                            {
                                                              "type": "microservice",
                                                              "config": {
                                                                "microserviceId": "getResultCodeForDiscrepancy",
                                                                "requestMethod": "get",
                                                                "params": {
                                                                  "bcn": "#repairUnitInfo.ITEM_BCN",
                                                                  "validateResult": 1
                                                                }
                                                              },
                                                              "responseDependents": {
                                                                "onSuccess": {
                                                                  "actions": [
                                                                    {
                                                                      "type": "context",
                                                                      "config": {
                                                                        "requestMethod": "add",
                                                                        "key": "resultCodesForDiscrepancy",
                                                                        "data": "responseData"
                                                                      }
                                                                    },
                                                                    {
                                                                      "type": "microservice",
                                                                      "config": {
                                                                        "microserviceId": "getstorageholdsubcode",
                                                                        "requestMethod": "get",
                                                                        "params": {
                                                                          "locationId": "#repairUnitInfo.LOCATION_ID",
                                                                          "clientId": "#repairUnitInfo.CLIENT_ID",
                                                                          "contractId": "#repairUnitInfo.CONTRACT_ID",
                                                                          "route": "#repairUnitInfo.ROUTE",
                                                                          "username": "#userAccountInfo.PersonalDetails.USERID",
                                                                          "workCenterId": "#repairUnitInfo.WORKCENTER_ID"
                                                                        }
                                                                      },
                                                                      "responseDependents": {
                                                                        "onSuccess": {
                                                                          "actions": [
                                                                            {
                                                                              "type": "context",
                                                                              "config": {
                                                                                "requestMethod": "add",
                                                                                "key": "holdCodesForDiscrepancy",
                                                                                "data": "responseData"
                                                                              }
                                                                            },
                                                                            {
                                                                              "type": "condition",
                                                                              "config": {
                                                                                "operation": "isValid",
                                                                                "lhs": "#repairUnitInfo.ROUTE_ID"
                                                                              },
                                                                              "responseDependents": {
                                                                                "onSuccess": {
                                                                                  "actions": [
                                                                                    {
                                                                                      "type": "condition",
                                                                                      "config": {
                                                                                        "operation": "isValid",
                                                                                        "lhs": "#repairUnitInfo.WORKCENTER_ID"
                                                                                      },
                                                                                      "responseDependents": {
                                                                                        "onSuccess": {
                                                                                          "actions": [
                                                                                            {
                                                                                              "type": "microservice",
                                                                                              "config": {
                                                                                                "microserviceId": "getSubProcessMenu",
                                                                                                "requestMethod": "get",
                                                                                                "params": {
                                                                                                  "userId": "#loginUUID.username",
                                                                                                  "locationId": "#userSelectedLocation",
                                                                                                  "clientId": "#userSelectedClient",
                                                                                                  "contractId": "#userSelectedContract",
                                                                                                  "wcId": "#repairUnitInfo.WORKCENTER_ID",
                                                                                                  "optId": "#repairUnitInfo.ROUTE_ID",
                                                                                                  "btt": "",
                                                                                                  "whId": "#repairUnitInfo.WAREHOUSE_ID",
                                                                                                  "operationType": "#userSelectedSubProcessType",
                                                                                                  "workCenterName": "#repairUnitInfo.WORKCENTER"
                                                                                                }
                                                                                              },
                                                                                              "responseDependents": {
                                                                                                "onSuccess": {
                                                                                                  "actions": [
                                                                                                    {
                                                                                                      "type": "context",
                                                                                                      "config": {
                                                                                                        "requestMethod": "add",
                                                                                                        "key": "SubprocessMenu",
                                                                                                        "data": "responseData"
                                                                                                      }
                                                                                                    },
                                                                                                    {
                                                                                                      "type": "microservice",
                                                                                                      "config": {
                                                                                                        "microserviceId": "getTimeInDetails",
                                                                                                        "requestMethod": "get",
                                                                                                        "params": {
                                                                                                          "workCenterName": "#repairUnitInfo.WORKCENTER",
                                                                                                          "itemId": "#repairUnitInfo.ITEM_ID",
                                                                                                          "userName": "#userAccountInfo.PersonalDetails.USERID",
                                                                                                          "locationId": "#repairUnitInfo.LOCATION_ID"
                                                                                                        }
                                                                                                      },
                                                                                                      "responseDependents": {
                                                                                                        "onSuccess": {
                                                                                                          "actions": [
                                                                                                            {
                                                                                                              "type": "updateComponent",
                                                                                                              "config": {
                                                                                                                "key": "errorTitleUUID",
                                                                                                                "properties": {
                                                                                                                  "titleValue": "",
                                                                                                                  "isShown": false
                                                                                                                }
                                                                                                              }
                                                                                                            },
                                                                                                            {
                                                                                                              "type": "context",
                                                                                                              "config": {
                                                                                                                "requestMethod": "add",
                                                                                                                "key": "getTimeInDetailsResp",
                                                                                                                "data": "responseData"
                                                                                                              }
                                                                                                            },
                                                                                                            {
                                                                                                              "type": "renderTemplate",
                                                                                                              "config": {
                                                                                                                "templateId": "repairAssessmentScreen.json",
                                                                                                                "mode": "local"
                                                                                                              }
                                                                                                            }
                                                                                                          ]
                                                                                                        },
                                                                                                        "onFailure": {
                                                                                                          "actions": [
                                                                                                            {
                                                                                                              "type": "context",
                                                                                                              "config": {
                                                                                                                "requestMethod": "add",
                                                                                                                "key": "getTimeInDetailsResp",
                                                                                                                "data": "responseData"
                                                                                                              }
                                                                                                            },
                                                                                                            {
                                                                                                              "type": "updateComponent",
                                                                                                              "config": {
                                                                                                                "key": "searchCriteriaErrorTitleUUID",
                                                                                                                "properties": {
                                                                                                                  "titleValue": "#getTimeInDetailsResp",
                                                                                                                  "isShown": true
                                                                                                                }
                                                                                                              }
                                                                                                            }
                                                                                                          ]
                                                                                                        }
                                                                                                      }
                                                                                                    }
                                                                                                  ]
                                                                                                },
                                                                                                "onFailure": {
                                                                                                  "actions": [
                                                                                                    {
                                                                                                      "type": "context",
                                                                                                      "config": {
                                                                                                        "requestMethod": "add",
                                                                                                        "key": "permission",
                                                                                                        "data": "responseData"
                                                                                                      }
                                                                                                    },
                                                                                                    {
                                                                                                      "type": "updateComponent",
                                                                                                      "config": {
                                                                                                        "key": "searchCriteriaErrorTitleUUID",
                                                                                                        "properties": {
                                                                                                          "titleValue": "#permission",
                                                                                                          "isShown": true
                                                                                                        }
                                                                                                      }
                                                                                                    }
                                                                                                  ]
                                                                                                }
                                                                                              }
                                                                                            }
                                                                                          ]
                                                                                        },
                                                                                        "onFailure": {
                                                                                          "actions": [
                                                                                            {
                                                                                              "type": "updateComponent",
                                                                                              "config": {
                                                                                                "key": "searchCriteriaErrorTitleUUID",
                                                                                                "properties": {
                                                                                                  "titleValue": "WorkCenter Is Not Assigned",
                                                                                                  "isShown": true
                                                                                                }
                                                                                              }
                                                                                            }
                                                                                          ]
                                                                                        }
                                                                                      }
                                                                                    }
                                                                                  ]
                                                                                },
                                                                                "onFailure": {
                                                                                  "actions": [
                                                                                    {
                                                                                      "type": "updateComponent",
                                                                                      "config": {
                                                                                        "key": "searchCriteriaErrorTitleUUID",
                                                                                        "properties": {
                                                                                          "titleValue": "Order Process Type Is Empty",
                                                                                          "isShown": true
                                                                                        }
                                                                                      }
                                                                                    }
                                                                                  ]
                                                                                }
                                                                              }
                                                                            }
                                                                          ]
                                                                        },
                                                                        "onFailure": {
                                                                          "actions": [
                                                                            {
                                                                              "type": "context",
                                                                              "config": {
                                                                                "requestMethod": "add",
                                                                                "key": "errorDisp",
                                                                                "data": "responseData"
                                                                              }
                                                                            },
                                                                            {
                                                                              "type": "updateComponent",
                                                                              "config": {
                                                                                "key": "searchCriteriaErrorTitleUUID",
                                                                                "properties": {
                                                                                  "titleValue": "#errorDisp",
                                                                                  "isShown": true
                                                                                }
                                                                              }
                                                                            }
                                                                          ]
                                                                        }
                                                                      }
                                                                    }
                                                                  ]
                                                                },
                                                                "onFailure": {
                                                                  "actions": [
                                                                    {
                                                                      "type": "context",
                                                                      "config": {
                                                                        "requestMethod": "add",
                                                                        "key": "errorDisp",
                                                                        "data": "responseData"
                                                                      }
                                                                    },
                                                                    {
                                                                      "type": "updateComponent",
                                                                      "config": {
                                                                        "key": "searchCriteriaErrorTitleUUID",
                                                                        "properties": {
                                                                          "titleValue": "#errorDisp",
                                                                          "isShown": true
                                                                        }
                                                                      }
                                                                    }
                                                                  ]
                                                                }
                                                              }
                                                            }
                                                          ]
                                                        },
                                                        "onFailure": {
                                                          "actions": [
                                                            {
                                                              "type": "context",
                                                              "config": {
                                                                "requestMethod": "add",
                                                                "key": "errorDisp",
                                                                "data": "responseData"
                                                              }
                                                            },
                                                            {
                                                              "type": "updateComponent",
                                                              "config": {
                                                                "key": "searchCriteriaErrorTitleUUID",
                                                                "properties": {
                                                                  "titleValue": "#errorDisp",
                                                                  "isShown": true
                                                                }
                                                              }
                                                            }
                                                          ]
                                                        }
                                                      }
                                                    }
                                                  ]
                                                },
                                                "onFailure": {
                                                  "actions": [
                                                    {
                                                      "type": "context",
                                                      "config": {
                                                        "requestMethod": "add",
                                                        "key": "errorDisp",
                                                        "data": "responseData"
                                                      }
                                                    },
                                                    {
                                                      "type": "updateComponent",
                                                      "config": {
                                                        "key": "searchCriteriaErrorTitleUUID",
                                                        "properties": {
                                                          "titleValue": "#errorDisp",
                                                          "isShown": true
                                                        }
                                                      }
                                                    }
                                                  ]
                                                }
                                              }
                                            }
                                          ]
                                        },
                                        "onFailure": {
                                          "actions": [
                                            {
                                              "type": "context",
                                              "config": {
                                                "requestMethod": "add",
                                                "key": "errorDisp",
                                                "data": "responseData"
                                              }
                                            },
                                            {
                                              "type": "updateComponent",
                                              "config": {
                                                "key": "searchCriteriaErrorTitleUUID",
                                                "properties": {
                                                  "titleValue": "#errorDisp",
                                                  "isShown": true
                                                }
                                              }
                                            }
                                          ]
                                        }
                                      }
                                    }
                                  ]
                                }
                              }
                            }
                          ]
                        }
                      }
                    }
                  ]
                },
                "onFailure": {
                  "actions": [
                    {
                      "type": "context",
                      "config": {
                        "requestMethod": "add",
                        "key": "errorDisp",
                        "data": "responseData"
                      }
                    },
                    {
                      "type": "updateComponent",
                      "config": {
                        "key": "searchCriteriaErrorTitleUUID",
                        "properties": {
                          "titleValue": "#errorDisp",
                          "isShown": true
                        }
                      }
                    }
                  ]
                }
              }
            }
          ]
        }
      ]
    }
  ],
  "footer": []
}
